{
  "minecraft:recipes/decorations/crafting_table": {
    "criteria": {
      "unlock_right_away": "2026-02-09 12:55:28 +0000"
    },
    "done": true
  },
  "minecraft:adventure/adventuring_time": {
    "criteria": {
      "minecraft:taiga": "2026-02-11 01:30:53 +0000",
      "minecraft:frozen_river": "2026-02-11 01:30:41 +0000",
      "minecraft:beach": "2026-02-09 13:01:19 +0000",
      "minecraft:river": "2026-02-10 03:10:40 +0000",
      "minecraft:stony_shore": "2026-02-10 03:48:28 +0000",
      "minecraft:snowy_plains": "2026-02-11 01:42:47 +0000",
      "minecraft:snowy_taiga": "2026-02-11 01:30:45 +0000",
      "minecraft:forest": "2026-02-09 12:55:29 +0000",
      "minecraft:ocean": "2026-02-10 03:17:05 +0000",
      "minecraft:plains": "2026-02-10 04:12:50 +0000"
    },
    "done": false
  },
  "farmersdelight:main/root": {
    "criteria": {
      "seeds": "2026-02-09 13:00:47 +0000"
    },
    "done": true
  },
  "takesapillage:root": {
    "criteria": {
      "always": "2026-02-09 13:00:48 +0000"
    },
    "done": true
  },
  "mowziesmobs:root": {
    "criteria": {
      "custom_test_name": "2026-02-09 13:00:48 +0000"
    },
    "done": true
  },
  "minecraft:recipes/misc/charcoal": {
    "criteria": {
      "has_log": "2026-02-09 13:00:57 +0000"
    },
    "done": true
  },
  "minecraft:recipes/building_blocks/oak_planks": {
    "criteria": {
      "has_logs": "2026-02-09 13:00:57 +0000"
    },
    "done": true
  },
  "minecraft:recipes/building_blocks/oak_wood": {
    "criteria": {
      "has_log": "2026-02-09 13:00:57 +0000"
    },
    "done": true
  },
  "minecraft:recipes/decorations/oak_sign": {
    "criteria": {
      "has_planks": "2026-02-09 13:40:31 +0000"
    },
    "done": true
  },
  "minecraft:recipes/redstone/oak_trapdoor": {
    "criteria": {
      "has_planks": "2026-02-09 13:40:31 +0000"
    },
    "done": true
  },
  "minecraft:recipes/misc/stick": {
    "criteria": {
      "has_planks": "2026-02-09 13:40:31 +0000"
    },
    "done": true
  },
  "minecraft:recipes/building_blocks/oak_stairs": {
    "criteria": {
      "has_planks": "2026-02-09 13:40:31 +0000"
    },
    "done": true
  },
  "minecraft:recipes/decorations/oak_fence": {
    "criteria": {
      "has_planks": "2026-02-09 13:40:31 +0000"
    },
    "done": true
  },
  "jeg:recipes/jeg/workbench": {
    "criteria": {
      "has_planks": "2026-02-09 13:40:31 +0000"
    },
    "done": true
  },
  "minecraft:recipes/redstone/oak_button": {
    "criteria": {
      "has_planks": "2026-02-09 13:40:31 +0000"
    },
    "done": true
  },
  "minecraft:recipes/building_blocks/oak_slab": {
    "criteria": {
      "has_planks": "2026-02-09 13:40:31 +0000"
    },
    "done": true
  },
  "minecraft:recipes/redstone/oak_fence_gate": {
    "criteria": {
      "has_planks": "2026-02-09 13:40:31 +0000"
    },
    "done": true
  },
  "minecraft:recipes/redstone/oak_pressure_plate": {
    "criteria": {
      "has_planks": "2026-02-09 13:40:31 +0000"
    },
    "done": true
  },
  "minecraft:recipes/redstone/oak_door": {
    "criteria": {
      "has_planks": "2026-02-09 13:40:31 +0000"
    },
    "done": true
  },
  "minecraft:recipes/decorations/barrel": {
    "criteria": {
      "has_planks": "2026-02-09 13:40:31 +0000"
    },
    "done": true
  },
  "sophisticatedbackpacks:recipes/misc/copper_backpack": {
    "criteria": {
      "has_backpack": "2026-02-09 14:21:54 +0000"
    },
    "done": true
  },
  "sophisticatedbackpacks:recipes/misc/iron_backpack": {
    "criteria": {
      "has_backpack": "2026-02-09 14:21:54 +0000"
    },
    "done": true
  },
  "minecraft:recipes/misc/iron_nugget_from_smelting": {
    "criteria": {
      "has_chainmail_chestplate": "2026-02-09 14:23:36 +0000"
    },
    "done": true
  },
  "minecraft:recipes/misc/iron_nugget_from_blasting": {
    "criteria": {
      "has_chainmail_chestplate": "2026-02-09 14:23:36 +0000"
    },
    "done": true
  },
  "minecraft:recipes/misc/cyan_dye": {
    "criteria": {
      "has_blue_dye": "2026-02-09 14:24:11 +0000"
    },
    "done": true
  },
  "minecraft:recipes/decorations/blue_candle": {
    "criteria": {
      "has_blue_dye": "2026-02-09 14:24:11 +0000"
    },
    "done": true
  },
  "minecraft:recipes/decorations/blue_stained_glass_pane_from_glass_pane": {
    "criteria": {
      "has_blue_dye": "2026-02-09 14:24:11 +0000"
    },
    "done": true
  },
  "minecraft:recipes/misc/magenta_dye_from_blue_red_pink": {
    "criteria": {
      "has_blue_dye": "2026-02-09 14:24:11 +0000"
    },
    "done": true
  },
  "minecraft:recipes/building_blocks/dye_blue_wool": {
    "criteria": {
      "has_needed_dye": "2026-02-09 14:24:11 +0000"
    },
    "done": true
  },
  "minecraft:recipes/misc/light_blue_dye_from_blue_white_dye": {
    "criteria": {
      "has_blue_dye": "2026-02-09 14:24:11 +0000"
    },
    "done": true
  },
  "minecraft:recipes/building_blocks/dye_blue_carpet": {
    "criteria": {
      "has_needed_dye": "2026-02-09 14:24:11 +0000"
    },
    "done": true
  },
  "minecraft:recipes/misc/purple_dye": {
    "criteria": {
      "has_blue_dye": "2026-02-09 14:24:11 +0000"
    },
    "done": true
  },
  "minecraft:recipes/building_blocks/dye_blue_bed": {
    "criteria": {
      "has_needed_dye": "2026-02-09 14:24:11 +0000"
    },
    "done": true
  },
  "minecraft:recipes/misc/magenta_dye_from_blue_red_white_dye": {
    "criteria": {
      "has_blue_dye": "2026-02-09 14:24:11 +0000"
    },
    "done": true
  },
  "minecraft:recipes/building_blocks/dye_brown_bed": {
    "criteria": {
      "has_needed_dye": "2026-02-09 14:24:14 +0000"
    },
    "done": true
  },
  "minecraft:recipes/decorations/brown_candle": {
    "criteria": {
      "has_brown_dye": "2026-02-09 14:24:14 +0000"
    },
    "done": true
  },
  "minecraft:recipes/building_blocks/dye_brown_wool": {
    "criteria": {
      "has_needed_dye": "2026-02-09 14:24:14 +0000"
    },
    "done": true
  },
  "minecraft:recipes/building_blocks/dye_brown_carpet": {
    "criteria": {
      "has_needed_dye": "2026-02-09 14:24:14 +0000"
    },
    "done": true
  },
  "minecraft:recipes/decorations/brown_stained_glass_pane_from_glass_pane": {
    "criteria": {
      "has_brown_dye": "2026-02-09 14:24:14 +0000"
    },
    "done": true
  },
  "minecraft:story/root": {
    "criteria": {
      "crafting_table": "2026-02-09 14:24:21 +0000"
    },
    "done": true
  },
  "minecraft:recipes/misc/wild_armor_trim_smithing_template": {
    "criteria": {
      "has_wild_armor_trim_smithing_template": "2026-02-09 14:30:58 +0000"
    },
    "done": true
  },
  "minecraft:recipes/misc/wild_armor_trim_smithing_template_smithing_trim": {
    "criteria": {
      "has_smithing_trim_template": "2026-02-09 14:30:58 +0000"
    },
    "done": true
  },
  "minecraft:recipes/misc/blue_dye": {
    "criteria": {
      "has_lapis_lazuli": "2026-02-09 14:31:04 +0000"
    },
    "done": true
  },
  "minecraft:recipes/building_blocks/lapis_block": {
    "criteria": {
      "has_lapis_lazuli": "2026-02-09 14:31:04 +0000"
    },
    "done": true
  },
  "minecraft:recipes/misc/wayfinder_armor_trim_smithing_template": {
    "criteria": {
      "has_wayfinder_armor_trim_smithing_template": "2026-02-09 14:31:36 +0000"
    },
    "done": true
  },
  "minecraft:recipes/misc/wayfinder_armor_trim_smithing_template_smithing_trim": {
    "criteria": {
      "has_smithing_trim_template": "2026-02-09 14:31:36 +0000"
    },
    "done": true
  },
  "minecraft:recipes/misc/ward_armor_trim_smithing_template_smithing_trim": {
    "criteria": {
      "has_smithing_trim_template": "2026-02-09 14:31:38 +0000"
    },
    "done": true
  },
  "minecraft:recipes/misc/ward_armor_trim_smithing_template": {
    "criteria": {
      "has_ward_armor_trim_smithing_template": "2026-02-09 14:31:38 +0000"
    },
    "done": true
  },
  "minecraft:recipes/decorations/chest": {
    "criteria": {
      "has_lots_of_items": "2026-02-09 14:31:40 +0000"
    },
    "done": true
  },
  "minecraft:recipes/misc/spire_armor_trim_smithing_template": {
    "criteria": {
      "has_spire_armor_trim_smithing_template": "2026-02-09 14:31:40 +0000"
    },
    "done": true
  },
  "minecraft:recipes/misc/spire_armor_trim_smithing_template_smithing_trim": {
    "criteria": {
      "has_smithing_trim_template": "2026-02-09 14:31:40 +0000"
    },
    "done": true
  },
  "minecraft:recipes/misc/rib_armor_trim_smithing_template_smithing_trim": {
    "criteria": {
      "has_smithing_trim_template": "2026-02-09 14:32:03 +0000"
    },
    "done": true
  },
  "minecraft:recipes/misc/rib_armor_trim_smithing_template": {
    "criteria": {
      "has_rib_armor_trim_smithing_template": "2026-02-09 14:32:03 +0000"
    },
    "done": true
  },
  "minecraft:recipes/misc/coast_armor_trim_smithing_template_smithing_trim": {
    "criteria": {
      "has_smithing_trim_template": "2026-02-09 14:32:07 +0000"
    },
    "done": true
  },
  "minecraft:recipes/misc/coast_armor_trim_smithing_template": {
    "criteria": {
      "has_coast_armor_trim_smithing_template": "2026-02-09 14:32:07 +0000"
    },
    "done": true
  },
  "minecraft:recipes/misc/tide_armor_trim_smithing_template": {
    "criteria": {
      "has_tide_armor_trim_smithing_template": "2026-02-09 14:32:09 +0000"
    },
    "done": true
  },
  "minecraft:recipes/misc/tide_armor_trim_smithing_template_smithing_trim": {
    "criteria": {
      "has_smithing_trim_template": "2026-02-09 14:32:09 +0000"
    },
    "done": true
  },
  "minecraft:adventure/trim_with_all_exclusive_armor_patterns": {
    "criteria": {
      "armor_trimmed_minecraft:tide_armor_trim_smithing_template_smithing_trim": "2026-02-09 14:32:19 +0000"
    },
    "done": false
  },
  "minecraft:adventure/trim_with_any_armor_pattern": {
    "criteria": {
      "armor_trimmed_minecraft:tide_armor_trim_smithing_template_smithing_trim": "2026-02-09 14:32:19 +0000"
    },
    "done": true
  },
  "minecraft:recipes/redstone/redstone_torch": {
    "criteria": {
      "has_redstone": "2026-02-09 14:32:45 +0000"
    },
    "done": true
  },
  "minecraft:recipes/tools/clock": {
    "criteria": {
      "has_redstone": "2026-02-09 14:32:45 +0000"
    },
    "done": true
  },
  "minecraft:recipes/redstone/note_block": {
    "criteria": {
      "has_redstone": "2026-02-09 14:32:45 +0000"
    },
    "done": true
  },
  "minecraft:recipes/redstone/target": {
    "criteria": {
      "has_redstone": "2026-02-09 14:32:45 +0000"
    },
    "done": true
  },
  "minecraft:recipes/tools/compass": {
    "criteria": {
      "has_redstone": "2026-02-09 14:32:45 +0000"
    },
    "done": true
  },
  "minecraft:recipes/redstone/dropper": {
    "criteria": {
      "has_redstone": "2026-02-09 14:32:45 +0000"
    },
    "done": true
  },
  "minecraft:recipes/redstone/redstone_block": {
    "criteria": {
      "has_redstone": "2026-02-09 14:32:45 +0000"
    },
    "done": true
  },
  "minecraft:recipes/redstone/piston": {
    "criteria": {
      "has_redstone": "2026-02-09 14:32:45 +0000"
    },
    "done": true
  },
  "minecraft:recipes/building_blocks/dye_red_carpet": {
    "criteria": {
      "has_needed_dye": "2026-02-09 14:33:08 +0000"
    },
    "done": true
  },
  "minecraft:recipes/building_blocks/dye_red_bed": {
    "criteria": {
      "has_needed_dye": "2026-02-09 14:33:08 +0000"
    },
    "done": true
  },
  "minecraft:recipes/building_blocks/dye_red_wool": {
    "criteria": {
      "has_needed_dye": "2026-02-09 14:33:08 +0000"
    },
    "done": true
  },
  "minecraft:recipes/misc/orange_dye_from_red_yellow": {
    "criteria": {
      "has_red_dye": "2026-02-09 14:33:08 +0000"
    },
    "done": true
  },
  "minecraft:recipes/decorations/red_candle": {
    "criteria": {
      "has_red_dye": "2026-02-09 14:33:08 +0000"
    },
    "done": true
  },
  "minecraft:recipes/decorations/red_stained_glass_pane_from_glass_pane": {
    "criteria": {
      "has_red_dye": "2026-02-09 14:33:08 +0000"
    },
    "done": true
  },
  "minecraft:recipes/misc/pink_dye_from_red_white_dye": {
    "criteria": {
      "has_red_dye": "2026-02-09 14:33:08 +0000"
    },
    "done": true
  },
  "minecraft:recipes/building_blocks/dye_black_carpet": {
    "criteria": {
      "has_needed_dye": "2026-02-09 14:33:23 +0000"
    },
    "done": true
  },
  "minecraft:recipes/building_blocks/dye_black_bed": {
    "criteria": {
      "has_needed_dye": "2026-02-09 14:33:23 +0000"
    },
    "done": true
  },
  "minecraft:recipes/decorations/black_stained_glass_pane_from_glass_pane": {
    "criteria": {
      "has_black_dye": "2026-02-09 14:33:23 +0000"
    },
    "done": true
  },
  "minecraft:recipes/misc/gray_dye": {
    "criteria": {
      "has_black_dye": "2026-02-09 14:33:23 +0000"
    },
    "done": true
  },
  "minecraft:recipes/misc/light_gray_dye_from_black_white_dye": {
    "criteria": {
      "has_black_dye": "2026-02-09 14:33:23 +0000"
    },
    "done": true
  },
  "minecraft:recipes/decorations/black_candle": {
    "criteria": {
      "has_black_dye": "2026-02-09 14:33:23 +0000"
    },
    "done": true
  },
  "minecraft:recipes/building_blocks/dye_black_wool": {
    "criteria": {
      "has_needed_dye": "2026-02-09 14:33:23 +0000"
    },
    "done": true
  },
  "alexsmobs:alexsmobs/root": {
    "criteria": {
      "useitem": "2026-02-09 14:33:30 +0000"
    },
    "done": true
  },
  "minecraft:husbandry/root": {
    "criteria": {
      "consumed_item": "2026-02-09 14:33:30 +0000"
    },
    "done": true
  },
  "minecraft:recipes/misc/mojang_banner_pattern": {
    "criteria": {
      "has_enchanted_golden_apple": "2026-02-09 14:35:32 +0000"
    },
    "done": true
  },
  "minecraft:recipes/misc/nether_brick": {
    "criteria": {
      "has_netherrack": "2026-02-09 14:35:49 +0000"
    },
    "done": true
  },
  "minecraft:recipes/building_blocks/light_gray_concrete_powder": {
    "criteria": {
      "has_sand": "2026-02-09 14:35:56 +0000"
    },
    "done": true
  },
  "minecraft:recipes/building_blocks/pink_concrete_powder": {
    "criteria": {
      "has_sand": "2026-02-09 14:35:56 +0000"
    },
    "done": true
  },
  "minecraft:recipes/building_blocks/red_concrete_powder": {
    "criteria": {
      "has_sand": "2026-02-09 14:35:56 +0000"
    },
    "done": true
  },
  "minecraft:recipes/building_blocks/brown_concrete_powder": {
    "criteria": {
      "has_sand": "2026-02-09 14:35:56 +0000"
    },
    "done": true
  },
  "minecraft:recipes/building_blocks/light_blue_concrete_powder": {
    "criteria": {
      "has_sand": "2026-02-09 14:35:56 +0000"
    },
    "done": true
  },
  "minecraft:recipes/building_blocks/glass": {
    "criteria": {
      "has_smelts_to_glass": "2026-02-09 14:35:56 +0000"
    },
    "done": true
  },
  "minecraft:recipes/building_blocks/green_concrete_powder": {
    "criteria": {
      "has_sand": "2026-02-09 14:35:56 +0000"
    },
    "done": true
  },
  "minecraft:recipes/building_blocks/blue_concrete_powder": {
    "criteria": {
      "has_sand": "2026-02-09 14:35:56 +0000"
    },
    "done": true
  },
  "minecraft:recipes/building_blocks/white_concrete_powder": {
    "criteria": {
      "has_sand": "2026-02-09 14:35:56 +0000"
    },
    "done": true
  },
  "minecraft:recipes/building_blocks/lime_concrete_powder": {
    "criteria": {
      "has_sand": "2026-02-09 14:35:56 +0000"
    },
    "done": true
  },
  "minecraft:recipes/building_blocks/orange_concrete_powder": {
    "criteria": {
      "has_sand": "2026-02-09 14:35:56 +0000"
    },
    "done": true
  },
  "minecraft:recipes/building_blocks/magenta_concrete_powder": {
    "criteria": {
      "has_sand": "2026-02-09 14:35:56 +0000"
    },
    "done": true
  },
  "minecraft:recipes/building_blocks/yellow_concrete_powder": {
    "criteria": {
      "has_sand": "2026-02-09 14:35:56 +0000"
    },
    "done": true
  },
  "minecraft:recipes/building_blocks/sandstone": {
    "criteria": {
      "has_sand": "2026-02-09 14:35:56 +0000"
    },
    "done": true
  },
  "minecraft:recipes/building_blocks/gray_concrete_powder": {
    "criteria": {
      "has_sand": "2026-02-09 14:35:56 +0000"
    },
    "done": true
  },
  "minecraft:recipes/building_blocks/black_concrete_powder": {
    "criteria": {
      "has_sand": "2026-02-09 14:35:56 +0000"
    },
    "done": true
  },
  "minecraft:recipes/building_blocks/purple_concrete_powder": {
    "criteria": {
      "has_sand": "2026-02-09 14:35:56 +0000"
    },
    "done": true
  },
  "minecraft:recipes/building_blocks/cyan_concrete_powder": {
    "criteria": {
      "has_sand": "2026-02-09 14:35:56 +0000"
    },
    "done": true
  },
  "minecraft:recipes/decorations/soul_lantern": {
    "criteria": {
      "has_soul_torch": "2026-02-09 14:37:24 +0000"
    },
    "done": true
  },
  "biomesoplenty:recipes/transportation/willow_boat": {
    "criteria": {
      "in_water": "2026-02-10 02:29:10 +0000"
    },
    "done": true
  },
  "biomesoplenty:recipes/transportation/fir_boat": {
    "criteria": {
      "in_water": "2026-02-10 02:29:10 +0000"
    },
    "done": true
  },
  "minecraft:recipes/transportation/cherry_boat": {
    "criteria": {
      "in_water": "2026-02-10 02:29:10 +0000"
    },
    "done": true
  },
  "biomesoplenty:recipes/transportation/umbran_boat": {
    "criteria": {
      "in_water": "2026-02-10 02:29:10 +0000"
    },
    "done": true
  },
  "minecraft:recipes/transportation/bamboo_raft": {
    "criteria": {
      "in_water": "2026-02-10 02:29:10 +0000"
    },
    "done": true
  },
  "biomesoplenty:recipes/transportation/dead_boat": {
    "criteria": {
      "in_water": "2026-02-10 02:29:10 +0000"
    },
    "done": true
  },
  "minecraft:recipes/transportation/spruce_boat": {
    "criteria": {
      "in_water": "2026-02-10 02:29:10 +0000"
    },
    "done": true
  },
  "biomesoplenty:recipes/transportation/magic_boat": {
    "criteria": {
      "in_water": "2026-02-10 02:29:10 +0000"
    },
    "done": true
  },
  "minecraft:recipes/transportation/birch_boat": {
    "criteria": {
      "in_water": "2026-02-10 02:29:10 +0000"
    },
    "done": true
  },
  "minecraft:recipes/transportation/oak_boat": {
    "criteria": {
      "in_water": "2026-02-10 02:29:10 +0000"
    },
    "done": true
  },
  "biomesoplenty:recipes/transportation/redwood_boat": {
    "criteria": {
      "in_water": "2026-02-10 02:29:10 +0000"
    },
    "done": true
  },
  "minecraft:recipes/transportation/mangrove_boat": {
    "criteria": {
      "in_water": "2026-02-10 02:29:10 +0000"
    },
    "done": true
  },
  "biomesoplenty:recipes/transportation/hellbark_boat": {
    "criteria": {
      "in_water": "2026-02-10 02:29:10 +0000"
    },
    "done": true
  },
  "biomesoplenty:recipes/transportation/jacaranda_boat": {
    "criteria": {
      "in_water": "2026-02-10 02:29:10 +0000"
    },
    "done": true
  },
  "biomesoplenty:recipes/transportation/mahogany_boat": {
    "criteria": {
      "in_water": "2026-02-10 02:29:10 +0000"
    },
    "done": true
  },
  "biomesoplenty:recipes/transportation/palm_boat": {
    "criteria": {
      "in_water": "2026-02-10 02:29:10 +0000"
    },
    "done": true
  },
  "minecraft:recipes/transportation/acacia_boat": {
    "criteria": {
      "in_water": "2026-02-10 02:29:10 +0000"
    },
    "done": true
  },
  "minecraft:recipes/transportation/jungle_boat": {
    "criteria": {
      "in_water": "2026-02-10 02:29:10 +0000"
    },
    "done": true
  },
  "minecraft:recipes/transportation/dark_oak_boat": {
    "criteria": {
      "in_water": "2026-02-10 02:29:10 +0000"
    },
    "done": true
  },
  "minecraft:recipes/decorations/yellow_candle": {
    "criteria": {
      "has_yellow_dye": "2026-02-10 02:31:32 +0000"
    },
    "done": true
  },
  "minecraft:recipes/building_blocks/dye_yellow_wool": {
    "criteria": {
      "has_needed_dye": "2026-02-10 02:31:32 +0000"
    },
    "done": true
  },
  "minecraft:recipes/building_blocks/dye_yellow_carpet": {
    "criteria": {
      "has_needed_dye": "2026-02-10 02:31:32 +0000"
    },
    "done": true
  },
  "minecraft:recipes/decorations/yellow_stained_glass_pane_from_glass_pane": {
    "criteria": {
      "has_yellow_dye": "2026-02-10 02:31:32 +0000"
    },
    "done": true
  },
  "minecraft:recipes/building_blocks/dye_yellow_bed": {
    "criteria": {
      "has_needed_dye": "2026-02-10 02:31:32 +0000"
    },
    "done": true
  },
  "minecraft:recipes/building_blocks/dye_green_bed": {
    "criteria": {
      "has_needed_dye": "2026-02-10 02:31:37 +0000"
    },
    "done": true
  },
  "minecraft:recipes/decorations/green_stained_glass_pane_from_glass_pane": {
    "criteria": {
      "has_green_dye": "2026-02-10 02:31:37 +0000"
    },
    "done": true
  },
  "minecraft:recipes/decorations/green_candle": {
    "criteria": {
      "has_green_dye": "2026-02-10 02:31:37 +0000"
    },
    "done": true
  },
  "minecraft:recipes/misc/lime_dye": {
    "criteria": {
      "has_green_dye": "2026-02-10 02:31:37 +0000"
    },
    "done": true
  },
  "minecraft:recipes/building_blocks/dye_green_carpet": {
    "criteria": {
      "has_needed_dye": "2026-02-10 02:31:37 +0000"
    },
    "done": true
  },
  "minecraft:recipes/building_blocks/dye_green_wool": {
    "criteria": {
      "has_needed_dye": "2026-02-10 02:31:37 +0000"
    },
    "done": true
  },
  "minecraft:recipes/building_blocks/dye_cyan_wool": {
    "criteria": {
      "has_needed_dye": "2026-02-10 02:31:42 +0000"
    },
    "done": true
  },
  "minecraft:recipes/building_blocks/dye_cyan_bed": {
    "criteria": {
      "has_needed_dye": "2026-02-10 02:31:42 +0000"
    },
    "done": true
  },
  "minecraft:recipes/decorations/cyan_candle": {
    "criteria": {
      "has_cyan_dye": "2026-02-10 02:31:42 +0000"
    },
    "done": true
  },
  "minecraft:recipes/decorations/cyan_stained_glass_pane_from_glass_pane": {
    "criteria": {
      "has_cyan_dye": "2026-02-10 02:31:42 +0000"
    },
    "done": true
  },
  "minecraft:recipes/building_blocks/dye_cyan_carpet": {
    "criteria": {
      "has_needed_dye": "2026-02-10 02:31:42 +0000"
    },
    "done": true
  },
  "minecraft:recipes/redstone/dispenser": {
    "criteria": {
      "has_bow": "2026-02-10 02:38:55 +0000"
    },
    "done": true
  },
  "minecraft:adventure/root": {
    "criteria": {
      "killed_by_something": "2026-02-10 03:04:58 +0000"
    },
    "done": true
  },
  "minecraft:recipes/building_blocks/birch_wood": {
    "criteria": {
      "has_log": "2026-02-10 03:06:03 +0000"
    },
    "done": true
  },
  "minecraft:recipes/building_blocks/birch_planks": {
    "criteria": {
      "has_logs": "2026-02-10 03:06:03 +0000"
    },
    "done": true
  },
  "minecraft:recipes/misc/paper": {
    "criteria": {
      "has_reeds": "2026-02-10 03:08:59 +0000"
    },
    "done": true
  },
  "minecraft:recipes/misc/sugar_from_sugar_cane": {
    "criteria": {
      "has_sugar_cane": "2026-02-10 03:08:59 +0000"
    },
    "done": true
  },
  "farmersdelight:recipes/cooking/dog_food": {
    "criteria": {
      "has_any_ingredient": "2026-02-10 03:15:38 +0000"
    },
    "done": true
  },
  "farmersdelight:recipes/building_blocks/organic_compost_from_rotten_flesh": {
    "criteria": {
      "has_rotten_flesh": "2026-02-10 03:15:38 +0000"
    },
    "done": true
  },
  "minecraft:recipes/decorations/ladder": {
    "criteria": {
      "has_stick": "2026-02-10 03:19:59 +0000"
    },
    "done": true
  },
  "farmersdelight:recipes/combat/flint_knife": {
    "criteria": {
      "has_stick": "2026-02-10 03:19:59 +0000"
    },
    "done": true
  },
  "minecraft:recipes/tools/wooden_axe": {
    "criteria": {
      "has_stick": "2026-02-10 03:19:59 +0000"
    },
    "done": true
  },
  "minecraft:recipes/decorations/campfire": {
    "criteria": {
      "has_stick": "2026-02-10 03:19:59 +0000"
    },
    "done": true
  },
  "minecraft:recipes/tools/wooden_hoe": {
    "criteria": {
      "has_stick": "2026-02-10 03:19:59 +0000"
    },
    "done": true
  },
  "minecraft:recipes/tools/wooden_pickaxe": {
    "criteria": {
      "has_stick": "2026-02-10 03:19:59 +0000"
    },
    "done": true
  },
  "minecraft:recipes/tools/wooden_shovel": {
    "criteria": {
      "has_stick": "2026-02-10 03:19:59 +0000"
    },
    "done": true
  },
  "minecraft:recipes/combat/wooden_sword": {
    "criteria": {
      "has_stick": "2026-02-10 03:19:59 +0000"
    },
    "done": true
  },
  "farmersdelight:recipes/decorations/cutting_board": {
    "criteria": {
      "has_stick": "2026-02-10 03:19:59 +0000"
    },
    "done": true
  },
  "minecraft:recipes/food/dried_kelp_from_smelting": {
    "criteria": {
      "has_kelp": "2026-02-10 03:22:11 +0000"
    },
    "done": true
  },
  "minecraft:recipes/food/dried_kelp_from_campfire_cooking": {
    "criteria": {
      "has_kelp": "2026-02-10 03:22:11 +0000"
    },
    "done": true
  },
  "minecraft:recipes/food/dried_kelp_from_smoking": {
    "criteria": {
      "has_kelp": "2026-02-10 03:22:11 +0000"
    },
    "done": true
  },
  "minecraft:adventure/kill_all_mobs": {
    "criteria": {
      "minecraft:pillager": "2026-02-11 01:24:40 +0000",
      "minecraft:skeleton": "2026-02-10 03:35:42 +0000",
      "minecraft:spider": "2026-02-10 03:51:34 +0000",
      "minecraft:creeper": "2026-02-11 01:27:06 +0000",
      "minecraft:stray": "2026-02-11 01:45:47 +0000",
      "minecraft:zombie": "2026-02-10 03:34:09 +0000",
      "minecraft:drowned": "2026-02-10 04:32:27 +0000"
    },
    "done": false
  },
  "minecraft:adventure/kill_a_mob": {
    "criteria": {
      "minecraft:zombie": "2026-02-10 03:34:09 +0000"
    },
    "done": true
  },
  "minecraft:recipes/misc/bone_meal": {
    "criteria": {
      "has_bone": "2026-02-10 03:35:42 +0000"
    },
    "done": true
  },
  "farmersdelight:recipes/cooking/bone_broth": {
    "criteria": {
      "has_bone": "2026-02-10 03:35:42 +0000"
    },
    "done": true
  },
  "minecraft:recipes/redstone/birch_button": {
    "criteria": {
      "has_planks": "2026-02-10 03:45:23 +0000"
    },
    "done": true
  },
  "minecraft:recipes/redstone/birch_door": {
    "criteria": {
      "has_planks": "2026-02-10 03:45:23 +0000"
    },
    "done": true
  },
  "minecraft:recipes/decorations/birch_fence": {
    "criteria": {
      "has_planks": "2026-02-10 03:45:23 +0000"
    },
    "done": true
  },
  "minecraft:recipes/decorations/birch_sign": {
    "criteria": {
      "has_planks": "2026-02-10 03:45:23 +0000"
    },
    "done": true
  },
  "minecraft:recipes/redstone/birch_fence_gate": {
    "criteria": {
      "has_planks": "2026-02-10 03:45:23 +0000"
    },
    "done": true
  },
  "minecraft:recipes/building_blocks/birch_slab": {
    "criteria": {
      "has_planks": "2026-02-10 03:45:23 +0000"
    },
    "done": true
  },
  "minecraft:recipes/building_blocks/birch_stairs": {
    "criteria": {
      "has_planks": "2026-02-10 03:45:23 +0000"
    },
    "done": true
  },
  "minecraft:recipes/redstone/birch_trapdoor": {
    "criteria": {
      "has_planks": "2026-02-10 03:45:23 +0000"
    },
    "done": true
  },
  "minecraft:recipes/redstone/birch_pressure_plate": {
    "criteria": {
      "has_planks": "2026-02-10 03:45:23 +0000"
    },
    "done": true
  },
  "biomesoplenty:recipes/transportation/jacaranda_chest_boat": {
    "criteria": {
      "has_boat": "2026-02-10 03:46:44 +0000"
    },
    "done": true
  },
  "minecraft:recipes/transportation/spruce_chest_boat": {
    "criteria": {
      "has_boat": "2026-02-10 03:46:44 +0000"
    },
    "done": true
  },
  "minecraft:recipes/transportation/jungle_chest_boat": {
    "criteria": {
      "has_boat": "2026-02-10 03:46:44 +0000"
    },
    "done": true
  },
  "minecraft:recipes/transportation/acacia_chest_boat": {
    "criteria": {
      "has_boat": "2026-02-10 03:46:44 +0000"
    },
    "done": true
  },
  "biomesoplenty:recipes/transportation/magic_chest_boat": {
    "criteria": {
      "has_boat": "2026-02-10 03:46:44 +0000"
    },
    "done": true
  },
  "minecraft:recipes/transportation/mangrove_chest_boat": {
    "criteria": {
      "has_boat": "2026-02-10 03:46:44 +0000"
    },
    "done": true
  },
  "biomesoplenty:recipes/transportation/fir_chest_boat": {
    "criteria": {
      "has_boat": "2026-02-10 03:46:44 +0000"
    },
    "done": true
  },
  "biomesoplenty:recipes/transportation/palm_chest_boat": {
    "criteria": {
      "has_boat": "2026-02-10 03:46:44 +0000"
    },
    "done": true
  },
  "biomesoplenty:recipes/transportation/redwood_chest_boat": {
    "criteria": {
      "has_boat": "2026-02-10 03:46:44 +0000"
    },
    "done": true
  },
  "minecraft:recipes/transportation/oak_chest_boat": {
    "criteria": {
      "has_boat": "2026-02-10 03:46:44 +0000"
    },
    "done": true
  },
  "minecraft:recipes/transportation/cherry_chest_boat": {
    "criteria": {
      "has_boat": "2026-02-10 03:46:44 +0000"
    },
    "done": true
  },
  "minecraft:recipes/transportation/birch_chest_boat": {
    "criteria": {
      "has_boat": "2026-02-10 03:46:44 +0000"
    },
    "done": true
  },
  "biomesoplenty:recipes/transportation/dead_chest_boat": {
    "criteria": {
      "has_boat": "2026-02-10 03:46:44 +0000"
    },
    "done": true
  },
  "minecraft:recipes/transportation/dark_oak_chest_boat": {
    "criteria": {
      "has_boat": "2026-02-10 03:46:44 +0000"
    },
    "done": true
  },
  "minecraft:recipes/transportation/bamboo_chest_raft": {
    "criteria": {
      "has_boat": "2026-02-10 03:46:44 +0000"
    },
    "done": true
  },
  "biomesoplenty:recipes/transportation/hellbark_chest_boat": {
    "criteria": {
      "has_boat": "2026-02-10 03:46:44 +0000"
    },
    "done": true
  },
  "biomesoplenty:recipes/transportation/mahogany_chest_boat": {
    "criteria": {
      "has_boat": "2026-02-10 03:46:44 +0000"
    },
    "done": true
  },
  "biomesoplenty:recipes/transportation/umbran_chest_boat": {
    "criteria": {
      "has_boat": "2026-02-10 03:46:44 +0000"
    },
    "done": true
  },
  "biomesoplenty:recipes/transportation/willow_chest_boat": {
    "criteria": {
      "has_boat": "2026-02-10 03:46:44 +0000"
    },
    "done": true
  },
  "minecraft:husbandry/balanced_diet": {
    "criteria": {
      "cooked_porkchop": "2026-02-10 03:47:26 +0000",
      "cooked_beef": "2026-02-10 04:34:04 +0000",
      "bread": "2026-02-11 02:03:34 +0000"
    },
    "done": false
  },
  "biomesoplenty:biomesoplenty/all_biomes": {
    "criteria": {
      "muskeg": "2026-02-11 01:30:00 +0000",
      "shrubland": "2026-02-10 03:48:20 +0000",
      "snowblossom_grove": "2026-02-11 01:30:26 +0000",
      "rocky_shrubland": "2026-02-10 03:48:44 +0000",
      "highland": "2026-02-10 04:02:38 +0000",
      "cold_desert": "2026-02-11 01:48:14 +0000",
      "coniferous_forest": "2026-02-10 04:14:25 +0000",
      "seasonal_orchard": "2026-02-11 01:29:53 +0000",
      "fir_clearing": "2026-02-10 04:23:12 +0000",
      "pumpkin_patch": "2026-02-11 01:29:59 +0000",
      "grassland": "2026-02-10 04:01:06 +0000",
      "snowy_maple_woods": "2026-02-11 01:30:43 +0000"
    },
    "done": false
  },
  "biomesoplenty:biomesoplenty/root": {
    "criteria": {
      "shrubland": "2026-02-10 03:48:20 +0000"
    },
    "done": true
  },
  "minecraft:recipes/redstone/lever": {
    "criteria": {
      "has_cobblestone": "2026-02-10 03:48:49 +0000"
    },
    "done": true
  },
  "minecraft:recipes/combat/stone_sword": {
    "criteria": {
      "has_cobblestone": "2026-02-10 03:48:49 +0000"
    },
    "done": true
  },
  "minecraft:recipes/decorations/cobblestone_wall": {
    "criteria": {
      "has_cobblestone": "2026-02-10 03:48:49 +0000"
    },
    "done": true
  },
  "minecraft:recipes/tools/stone_axe": {
    "criteria": {
      "has_cobblestone": "2026-02-10 03:48:49 +0000"
    },
    "done": true
  },
  "minecraft:story/mine_stone": {
    "criteria": {
      "get_stone": "2026-02-10 03:48:49 +0000"
    },
    "done": true
  },
  "minecraft:recipes/decorations/furnace": {
    "criteria": {
      "has_cobblestone": "2026-02-10 03:48:49 +0000"
    },
    "done": true
  },
  "minecraft:recipes/building_blocks/cobblestone_slab_from_cobblestone_stonecutting": {
    "criteria": {
      "has_cobblestone": "2026-02-10 03:48:49 +0000"
    },
    "done": true
  },
  "minecraft:recipes/building_blocks/stone": {
    "criteria": {
      "has_cobblestone": "2026-02-10 03:48:49 +0000"
    },
    "done": true
  },
  "minecraft:recipes/tools/stone_pickaxe": {
    "criteria": {
      "has_cobblestone": "2026-02-10 03:48:49 +0000"
    },
    "done": true
  },
  "minecraft:recipes/building_blocks/cobblestone_slab": {
    "criteria": {
      "has_cobblestone": "2026-02-10 03:48:49 +0000"
    },
    "done": true
  },
  "minecraft:recipes/decorations/cobblestone_wall_from_cobblestone_stonecutting": {
    "criteria": {
      "has_cobblestone": "2026-02-10 03:48:49 +0000"
    },
    "done": true
  },
  "minecraft:recipes/building_blocks/cobblestone_stairs_from_cobblestone_stonecutting": {
    "criteria": {
      "has_cobblestone": "2026-02-10 03:48:49 +0000"
    },
    "done": true
  },
  "minecraft:recipes/building_blocks/cobblestone_stairs": {
    "criteria": {
      "has_cobblestone": "2026-02-10 03:48:49 +0000"
    },
    "done": true
  },
  "minecraft:recipes/tools/stone_hoe": {
    "criteria": {
      "has_cobblestone": "2026-02-10 03:48:49 +0000"
    },
    "done": true
  },
  "minecraft:recipes/tools/stone_shovel": {
    "criteria": {
      "has_cobblestone": "2026-02-10 03:48:49 +0000"
    },
    "done": true
  },
  "minecraft:recipes/decorations/torch": {
    "criteria": {
      "has_stone_pickaxe": "2026-02-10 03:49:37 +0000"
    },
    "done": true
  },
  "minecraft:story/upgrade_tools": {
    "criteria": {
      "stone_pickaxe": "2026-02-10 03:49:37 +0000"
    },
    "done": true
  },
  "minecraft:recipes/building_blocks/coal_block": {
    "criteria": {
      "has_coal": "2026-02-10 03:49:49 +0000"
    },
    "done": true
  },
  "minecraft:recipes/building_blocks/raw_iron_block": {
    "criteria": {
      "has_raw_iron": "2026-02-10 03:50:01 +0000"
    },
    "done": true
  },
  "minecraft:recipes/misc/iron_ingot_from_smelting_raw_iron": {
    "criteria": {
      "has_raw_iron": "2026-02-10 03:50:01 +0000"
    },
    "done": true
  },
  "minecraft:recipes/misc/iron_ingot_from_blasting_raw_iron": {
    "criteria": {
      "has_raw_iron": "2026-02-10 03:50:01 +0000"
    },
    "done": true
  },
  "minecraft:recipes/misc/copper_ingot_from_blasting_raw_copper": {
    "criteria": {
      "has_raw_copper": "2026-02-10 03:50:12 +0000"
    },
    "done": true
  },
  "minecraft:recipes/building_blocks/raw_copper_block": {
    "criteria": {
      "has_raw_copper": "2026-02-10 03:50:12 +0000"
    },
    "done": true
  },
  "minecraft:recipes/misc/copper_ingot_from_smelting_raw_copper": {
    "criteria": {
      "has_raw_copper": "2026-02-10 03:50:12 +0000"
    },
    "done": true
  },
  "minecraft:recipes/combat/bow": {
    "criteria": {
      "has_string": "2026-02-10 03:51:35 +0000"
    },
    "done": true
  },
  "minecraft:recipes/tools/fishing_rod": {
    "criteria": {
      "has_string": "2026-02-10 03:51:35 +0000"
    },
    "done": true
  },
  "minecraft:recipes/redstone/tripwire_hook": {
    "criteria": {
      "has_string": "2026-02-10 03:51:35 +0000"
    },
    "done": true
  },
  "minecraft:recipes/decorations/candle": {
    "criteria": {
      "has_string": "2026-02-10 03:51:35 +0000"
    },
    "done": true
  },
  "minecraft:recipes/building_blocks/white_wool_from_string": {
    "criteria": {
      "has_string": "2026-02-10 03:51:35 +0000"
    },
    "done": true
  },
  "minecraft:recipes/combat/crossbow": {
    "criteria": {
      "has_string": "2026-02-10 03:51:35 +0000"
    },
    "done": true
  },
  "minecraft:recipes/decorations/loom": {
    "criteria": {
      "has_string": "2026-02-10 03:51:35 +0000"
    },
    "done": true
  },
  "farmersdelight:recipes/cooking/noodle_soup": {
    "criteria": {
      "has_any_ingredient": "2026-02-10 03:53:19 +0000"
    },
    "done": true
  },
  "minecraft:recipes/food/cooked_porkchop_from_campfire_cooking": {
    "criteria": {
      "has_porkchop": "2026-02-10 03:53:19 +0000"
    },
    "done": true
  },
  "farmersdelight:recipes/cooking/pumpkin_soup": {
    "criteria": {
      "has_any_ingredient": "2026-02-10 03:53:19 +0000"
    },
    "done": true
  },
  "minecraft:recipes/food/cooked_porkchop": {
    "criteria": {
      "has_porkchop": "2026-02-10 03:53:19 +0000"
    },
    "done": true
  },
  "minecraft:recipes/food/cooked_porkchop_from_smoking": {
    "criteria": {
      "has_porkchop": "2026-02-10 03:53:19 +0000"
    },
    "done": true
  },
  "minecraft:recipes/decorations/smoker": {
    "criteria": {
      "has_furnace": "2026-02-10 03:54:37 +0000"
    },
    "done": true
  },
  "minecraft:recipes/combat/iron_leggings": {
    "criteria": {
      "has_iron_ingot": "2026-02-10 03:54:52 +0000"
    },
    "done": true
  },
  "minecraft:recipes/combat/iron_chestplate": {
    "criteria": {
      "has_iron_ingot": "2026-02-10 03:54:52 +0000"
    },
    "done": true
  },
  "minecraft:recipes/misc/iron_nugget": {
    "criteria": {
      "has_iron_ingot": "2026-02-10 03:54:52 +0000"
    },
    "done": true
  },
  "minecraft:recipes/misc/bucket": {
    "criteria": {
      "has_iron_ingot": "2026-02-10 03:54:52 +0000"
    },
    "done": true
  },
  "minecraft:recipes/combat/iron_helmet": {
    "criteria": {
      "has_iron_ingot": "2026-02-10 03:54:52 +0000"
    },
    "done": true
  },
  "minecraft:recipes/transportation/minecart": {
    "criteria": {
      "has_iron_ingot": "2026-02-10 03:54:52 +0000"
    },
    "done": true
  },
  "minecraft:recipes/tools/iron_hoe": {
    "criteria": {
      "has_iron_ingot": "2026-02-10 03:54:52 +0000"
    },
    "done": true
  },
  "minecraft:story/smelt_iron": {
    "criteria": {
      "iron": "2026-02-10 03:54:52 +0000"
    },
    "done": true
  },
  "minecraft:recipes/tools/shears": {
    "criteria": {
      "has_iron_ingot": "2026-02-10 03:54:52 +0000"
    },
    "done": true
  },
  "minecraft:recipes/decorations/chain": {
    "criteria": {
      "has_iron_ingot": "2026-02-10 03:54:52 +0000"
    },
    "done": true
  },
  "minecraft:recipes/building_blocks/iron_block": {
    "criteria": {
      "has_iron_ingot": "2026-02-10 03:54:52 +0000"
    },
    "done": true
  },
  "farmersdelight:recipes/decorations/cooking_pot": {
    "criteria": {
      "has_iron_ingot": "2026-02-10 03:54:52 +0000"
    },
    "done": true
  },
  "minecraft:recipes/decorations/smithing_table": {
    "criteria": {
      "has_iron_ingot": "2026-02-10 03:54:52 +0000"
    },
    "done": true
  },
  "minecraft:recipes/combat/iron_sword": {
    "criteria": {
      "has_iron_ingot": "2026-02-10 03:54:52 +0000"
    },
    "done": true
  },
  "minecraft:recipes/tools/iron_pickaxe": {
    "criteria": {
      "has_iron_ingot": "2026-02-10 03:54:52 +0000"
    },
    "done": true
  },
  "minecraft:recipes/combat/shield": {
    "criteria": {
      "has_iron_ingot": "2026-02-10 03:54:52 +0000"
    },
    "done": true
  },
  "minecraft:recipes/redstone/hopper": {
    "criteria": {
      "has_iron_ingot": "2026-02-10 03:54:52 +0000"
    },
    "done": true
  },
  "minecraft:recipes/decorations/iron_bars": {
    "criteria": {
      "has_iron_ingot": "2026-02-10 03:54:52 +0000"
    },
    "done": true
  },
  "minecraft:recipes/combat/iron_boots": {
    "criteria": {
      "has_iron_ingot": "2026-02-10 03:54:52 +0000"
    },
    "done": true
  },
  "minecraft:recipes/decorations/lantern": {
    "criteria": {
      "has_iron_ingot": "2026-02-10 03:54:52 +0000"
    },
    "done": true
  },
  "minecraft:recipes/tools/iron_shovel": {
    "criteria": {
      "has_iron_ingot": "2026-02-10 03:54:52 +0000"
    },
    "done": true
  },
  "minecraft:recipes/redstone/iron_trapdoor": {
    "criteria": {
      "has_iron_ingot": "2026-02-10 03:54:52 +0000"
    },
    "done": true
  },
  "minecraft:recipes/tools/iron_axe": {
    "criteria": {
      "has_iron_ingot": "2026-02-10 03:54:52 +0000"
    },
    "done": true
  },
  "farmersdelight:recipes/combat/iron_knife": {
    "criteria": {
      "has_iron_ingot": "2026-02-10 03:54:52 +0000"
    },
    "done": true
  },
  "minecraft:recipes/redstone/iron_door": {
    "criteria": {
      "has_iron_ingot": "2026-02-10 03:54:52 +0000"
    },
    "done": true
  },
  "minecraft:recipes/redstone/heavy_weighted_pressure_plate": {
    "criteria": {
      "has_iron_ingot": "2026-02-10 03:54:52 +0000"
    },
    "done": true
  },
  "minecraft:story/deflect_arrow": {
    "criteria": {
      "deflected_projectile": "2026-02-10 03:56:14 +0000"
    },
    "done": true
  },
  "minecraft:story/iron_tools": {
    "criteria": {
      "iron_pickaxe": "2026-02-10 04:06:31 +0000"
    },
    "done": true
  },
  "minecraft:recipes/combat/arrow": {
    "criteria": {
      "has_feather": "2026-02-10 04:06:52 +0000"
    },
    "done": true
  },
  "minecraft:recipes/brewing/cauldron": {
    "criteria": {
      "has_water_bucket": "2026-02-10 04:08:30 +0000"
    },
    "done": true
  },
  "minecraft:story/obtain_armor": {
    "criteria": {
      "iron_helmet": "2026-02-10 04:13:18 +0000"
    },
    "done": true
  },
  "minecraft:recipes/misc/red_dye_from_rose_bush": {
    "criteria": {
      "has_rose_bush": "2026-02-10 04:13:37 +0000"
    },
    "done": true
  },
  "minecraft:recipes/misc/coal": {
    "criteria": {
      "has_coal_block": "2026-02-10 04:14:45 +0000"
    },
    "done": true
  },
  "farmersdelight:main/get_fd_seed": {
    "criteria": {
      "tomato_seeds": "2026-02-10 04:17:33 +0000"
    },
    "done": true
  },
  "farmersdelight:recipes/cooking/fish_stew": {
    "criteria": {
      "has_any_ingredient": "2026-02-10 04:18:56 +0000"
    },
    "done": true
  },
  "farmersdelight:recipes/food/barbecue_stick": {
    "criteria": {
      "has_onion": "2026-02-10 04:18:56 +0000"
    },
    "done": true
  },
  "farmersdelight:recipes/cooking/fried_rice": {
    "criteria": {
      "has_any_ingredient": "2026-02-10 04:18:56 +0000"
    },
    "done": true
  },
  "farmersdelight:recipes/cooking/dumplings": {
    "criteria": {
      "has_any_ingredient": "2026-02-10 04:18:56 +0000"
    },
    "done": true
  },
  "farmersdelight:recipes/cooking/ratatouille": {
    "criteria": {
      "has_any_ingredient": "2026-02-10 04:18:56 +0000"
    },
    "done": true
  },
  "farmersdelight:recipes/building_blocks/onion_crate": {
    "criteria": {
      "has_onion": "2026-02-10 04:18:56 +0000"
    },
    "done": true
  },
  "farmersdelight:recipes/cooking/vegetable_soup": {
    "criteria": {
      "has_any_ingredient": "2026-02-10 04:18:56 +0000"
    },
    "done": true
  },
  "farmersdelight:recipes/cooking/apple_cider": {
    "criteria": {
      "has_apple": "2026-02-10 04:20:47 +0000"
    },
    "done": true
  },
  "minecraft:recipes/food/baked_potato_from_campfire_cooking": {
    "criteria": {
      "has_potato": "2026-02-10 04:20:49 +0000"
    },
    "done": true
  },
  "minecraft:recipes/food/baked_potato": {
    "criteria": {
      "has_potato": "2026-02-10 04:20:49 +0000"
    },
    "done": true
  },
  "farmersdelight:recipes/cooking/baked_cod_stew": {
    "criteria": {
      "has_any_ingredient": "2026-02-10 04:20:49 +0000"
    },
    "done": true
  },
  "farmersdelight:recipes/cooking/beef_stew": {
    "criteria": {
      "has_any_ingredient": "2026-02-10 04:20:49 +0000"
    },
    "done": true
  },
  "minecraft:recipes/food/baked_potato_from_smoking": {
    "criteria": {
      "has_potato": "2026-02-10 04:20:49 +0000"
    },
    "done": true
  },
  "biomesoplenty:recipes/building_blocks/fir_wood": {
    "criteria": {
      "has_log": "2026-02-10 04:23:15 +0000"
    },
    "done": true
  },
  "biomesoplenty:recipes/building_blocks/fir_planks": {
    "criteria": {
      "has_logs": "2026-02-10 04:23:15 +0000"
    },
    "done": true
  },
  "minecraft:recipes/food/cooked_beef_from_smoking": {
    "criteria": {
      "has_beef": "2026-02-10 04:23:26 +0000"
    },
    "done": true
  },
  "farmersdelight:recipes/cooking/pasta_with_meatballs": {
    "criteria": {
      "has_any_ingredient": "2026-02-10 04:23:26 +0000"
    },
    "done": true
  },
  "minecraft:recipes/food/cooked_beef": {
    "criteria": {
      "has_beef": "2026-02-10 04:23:26 +0000"
    },
    "done": true
  },
  "minecraft:recipes/food/cooked_beef_from_campfire_cooking": {
    "criteria": {
      "has_beef": "2026-02-10 04:23:26 +0000"
    },
    "done": true
  },
  "biomesoplenty:recipes/building_blocks/fir_slab": {
    "criteria": {
      "has_planks": "2026-02-10 04:23:48 +0000"
    },
    "done": true
  },
  "biomesoplenty:recipes/redstone/fir_fence_gate": {
    "criteria": {
      "has_planks": "2026-02-10 04:23:48 +0000"
    },
    "done": true
  },
  "biomesoplenty:recipes/decorations/fir_fence": {
    "criteria": {
      "has_planks": "2026-02-10 04:23:48 +0000"
    },
    "done": true
  },
  "biomesoplenty:recipes/decorations/fir_sign": {
    "criteria": {
      "has_fir_planks": "2026-02-10 04:23:48 +0000"
    },
    "done": true
  },
  "biomesoplenty:recipes/redstone/fir_button": {
    "criteria": {
      "has_planks": "2026-02-10 04:23:48 +0000"
    },
    "done": true
  },
  "biomesoplenty:recipes/redstone/fir_door": {
    "criteria": {
      "has_planks": "2026-02-10 04:23:48 +0000"
    },
    "done": true
  },
  "biomesoplenty:recipes/building_blocks/fir_stairs": {
    "criteria": {
      "has_planks": "2026-02-10 04:23:48 +0000"
    },
    "done": true
  },
  "biomesoplenty:recipes/redstone/fir_trapdoor": {
    "criteria": {
      "has_planks": "2026-02-10 04:23:48 +0000"
    },
    "done": true
  },
  "biomesoplenty:recipes/redstone/fir_pressure_plate": {
    "criteria": {
      "has_planks": "2026-02-10 04:23:48 +0000"
    },
    "done": true
  },
  "minecraft:recipes/misc/iron_ingot_from_iron_block": {
    "criteria": {
      "has_iron_block": "2026-02-10 04:33:48 +0000"
    },
    "done": true
  },
  "minecraft:recipes/decorations/anvil": {
    "criteria": {
      "has_iron_block": "2026-02-10 04:33:48 +0000"
    },
    "done": true
  },
  "minecraft:adventure/sleep_in_bed": {
    "criteria": {
      "slept_in_bed": "2026-02-10 04:34:52 +0000"
    },
    "done": true
  },
  "minecraft:recipes/building_blocks/coarse_dirt": {
    "criteria": {
      "has_gravel": "2026-02-10 04:46:26 +0000"
    },
    "done": true
  },
  "minecraft:recipes/decorations/fletching_table": {
    "criteria": {
      "has_flint": "2026-02-10 04:47:59 +0000"
    },
    "done": true
  },
  "minecraft:recipes/tools/flint_and_steel": {
    "criteria": {
      "has_flint": "2026-02-10 04:47:59 +0000"
    },
    "done": true
  },
  "minecraft:recipes/decorations/black_stained_glass_pane": {
    "criteria": {
      "has_glass": "2026-02-10 05:01:29 +0000"
    },
    "done": true
  },
  "minecraft:recipes/decorations/composter": {
    "criteria": {
      "has_wood_slab": "2026-02-11 00:39:40 +0000"
    },
    "done": true
  },
  "farmersdelight:main/place_cooking_pot": {
    "criteria": {
      "cooking_pot": "2026-02-11 00:46:20 +0000"
    },
    "done": true
  },
  "farmersdelight:main/place_skillet": {
    "criteria": {
      "skillet": "2026-02-11 00:46:37 +0000"
    },
    "done": true
  },
  "farmersdelight:recipes/misc/iron_nugget_from_blasting_knife": {
    "criteria": {
      "has_iron_knife": "2026-02-11 00:47:02 +0000"
    },
    "done": true
  },
  "farmersdelight:recipes/misc/iron_nugget_from_smelting_knife": {
    "criteria": {
      "has_iron_knife": "2026-02-11 00:47:02 +0000"
    },
    "done": true
  },
  "farmersdelight:main/craft_knife": {
    "criteria": {
      "iron_knife": "2026-02-11 00:47:02 +0000"
    },
    "done": true
  },
  "farmersdelight:recipes/decorations/rope_from_safety_net": {
    "criteria": {
      "has_safety_net": "2026-02-11 00:47:56 +0000"
    },
    "done": true
  },
  "farmersdelight:recipes/cooking/mushroom_rice": {
    "criteria": {
      "has_any_ingredient": "2026-02-11 00:54:33 +0000"
    },
    "done": true
  },
  "farmersdelight:recipes/cooking/cooked_rice": {
    "criteria": {
      "has_rice": "2026-02-11 00:54:33 +0000"
    },
    "done": true
  },
  "farmersdelight:recipes/building_blocks/rice_bag": {
    "criteria": {
      "has_rice": "2026-02-11 00:54:33 +0000"
    },
    "done": true
  },
  "farmersdelight:main/plant_all_crops": {
    "criteria": {
      "cabbage": "2026-02-11 00:56:43 +0000",
      "tomato": "2026-02-11 00:55:36 +0000",
      "beetroot": "2026-02-11 01:21:22 +0000",
      "wheat": "2026-02-11 02:01:13 +0000"
    },
    "done": false
  },
  "minecraft:recipes/misc/white_dye": {
    "criteria": {
      "has_bone_meal": "2026-02-11 01:01:57 +0000"
    },
    "done": true
  },
  "minecraft:recipes/building_blocks/bone_block": {
    "criteria": {
      "has_bone_meal": "2026-02-11 01:01:57 +0000"
    },
    "done": true
  },
  "minecraft:recipes/building_blocks/polished_deepslate": {
    "criteria": {
      "has_cobbled_deepslate": "2026-02-11 01:36:21 +0000"
    },
    "done": true
  },
  "farmersdelight:recipes/food/nether_salad": {
    "criteria": {
      "has_bowl": "2026-02-11 02:00:18 +0000"
    },
    "done": true
  },
  "minecraft:recipes/building_blocks/deepslate_tile_stairs_from_cobbled_deepslate_stonecutting": {
    "criteria": {
      "has_cobbled_deepslate": "2026-02-11 01:36:21 +0000"
    },
    "done": true
  },
  "minecraft:recipes/food/cooked_mutton_from_smoking": {
    "criteria": {
      "has_mutton": "2026-02-11 01:44:27 +0000"
    },
    "done": true
  },
  "minecraft:recipes/building_blocks/light_blue_stained_glass": {
    "criteria": {
      "has_glass": "2026-02-11 01:09:02 +0000"
    },
    "done": true
  },
  "minecraft:recipes/building_blocks/green_stained_glass": {
    "criteria": {
      "has_glass": "2026-02-11 01:09:02 +0000"
    },
    "done": true
  },
  "farmersdelight:recipes/cooking/stuffed_pumpkin_block": {
    "criteria": {
      "has_pumpkin": "2026-02-11 01:45:03 +0000"
    },
    "done": true
  },
  "minecraft:recipes/building_blocks/deepslate_brick_stairs_from_cobbled_deepslate_stonecutting": {
    "criteria": {
      "has_cobbled_deepslate": "2026-02-11 01:36:21 +0000"
    },
    "done": true
  },
  "minecraft:recipes/building_blocks/brown_stained_glass": {
    "criteria": {
      "has_glass": "2026-02-11 01:09:02 +0000"
    },
    "done": true
  },
  "minecraft:recipes/building_blocks/blue_stained_glass": {
    "criteria": {
      "has_glass": "2026-02-11 01:09:02 +0000"
    },
    "done": true
  },
  "minecraft:recipes/food/beetroot_soup": {
    "criteria": {
      "has_beetroot": "2026-02-11 01:21:26 +0000"
    },
    "done": true
  },
  "minecraft:recipes/building_blocks/andesite_stairs": {
    "criteria": {
      "has_andesite": "2026-02-11 01:36:06 +0000"
    },
    "done": true
  },
  "minecraft:recipes/misc/gold_ingot_from_blasting_raw_gold": {
    "criteria": {
      "has_raw_gold": "2026-02-11 01:39:46 +0000"
    },
    "done": true
  },
  "minecraft:recipes/building_blocks/orange_stained_glass": {
    "criteria": {
      "has_glass": "2026-02-11 01:09:02 +0000"
    },
    "done": true
  },
  "minecraft:recipes/misc/bowl": {
    "criteria": {
      "has_the_recipe": "2026-02-11 02:00:17 +0000"
    },
    "done": true
  },
  "farmersdelight:recipes/food/cooked_mutton_chops": {
    "criteria": {
      "cooked_mutton_chops": "2026-02-11 01:50:50 +0000"
    },
    "done": true
  },
  "alexsmobs:alexsmobs/banana_slug": {
    "criteria": {
      "killed_by": "2026-02-11 01:12:00 +0000"
    },
    "done": true
  },
  "minecraft:recipes/decorations/painting": {
    "criteria": {
      "has_wool": "2026-02-11 01:44:27 +0000"
    },
    "done": true
  },
  "minecraft:recipes/decorations/andesite_wall_from_andesite_stonecutting": {
    "criteria": {
      "has_andesite": "2026-02-11 01:36:06 +0000"
    },
    "done": true
  },
  "minecraft:recipes/building_blocks/pink_stained_glass": {
    "criteria": {
      "has_glass": "2026-02-11 01:09:02 +0000"
    },
    "done": true
  },
  "minecraft:recipes/building_blocks/black_stained_glass": {
    "criteria": {
      "has_glass": "2026-02-11 01:09:02 +0000"
    },
    "done": true
  },
  "minecraft:recipes/building_blocks/chiseled_deepslate_from_cobbled_deepslate_stonecutting": {
    "criteria": {
      "has_cobbled_deepslate": "2026-02-11 01:36:21 +0000"
    },
    "done": true
  },
  "minecraft:recipes/building_blocks/gray_stained_glass": {
    "criteria": {
      "has_glass": "2026-02-11 01:09:02 +0000"
    },
    "done": true
  },
  "minecraft:recipes/misc/pumpkin_seeds": {
    "criteria": {
      "has_pumpkin": "2026-02-11 01:45:03 +0000"
    },
    "done": true
  },
  "minecraft:recipes/building_blocks/cobbled_deepslate_slab": {
    "criteria": {
      "has_cobbled_deepslate": "2026-02-11 01:36:21 +0000"
    },
    "done": true
  },
  "farmersdelight:recipes/cooking/cabbage_rolls": {
    "criteria": {
      "has_any_ingredient": "2026-02-11 02:01:17 +0000"
    },
    "done": true
  },
  "minecraft:recipes/decorations/cobbled_deepslate_wall_from_cobbled_deepslate_stonecutting": {
    "criteria": {
      "has_cobbled_deepslate": "2026-02-11 01:36:21 +0000"
    },
    "done": true
  },
  "minecraft:recipes/building_blocks/polished_andesite_slab_from_andesite_stonecutting": {
    "criteria": {
      "has_andesite": "2026-02-11 01:36:06 +0000"
    },
    "done": true
  },
  "minecraft:recipes/redstone/lightning_rod": {
    "criteria": {
      "has_copper_ingot": "2026-02-11 01:08:27 +0000"
    },
    "done": true
  },
  "minecraft:recipes/building_blocks/lime_stained_glass": {
    "criteria": {
      "has_glass": "2026-02-11 01:09:02 +0000"
    },
    "done": true
  },
  "farmersdelight:recipes/food/bacon_sandwich": {
    "criteria": {
      "has_bacon": "2026-02-11 01:53:24 +0000"
    },
    "done": true
  },
  "minecraft:recipes/decorations/cobbled_deepslate_wall": {
    "criteria": {
      "has_cobbled_deepslate": "2026-02-11 01:36:21 +0000"
    },
    "done": true
  },
  "minecraft:recipes/decorations/polished_deepslate_wall_from_cobbled_deepslate_stonecutting": {
    "criteria": {
      "has_cobbled_deepslate": "2026-02-11 01:36:21 +0000"
    },
    "done": true
  },
  "farmersdelight:recipes/food/cooked_mutton_chops_from_smoking": {
    "criteria": {
      "cooked_mutton_chops": "2026-02-11 01:50:50 +0000"
    },
    "done": true
  },
  "minecraft:recipes/building_blocks/cobbled_deepslate_stairs_from_cobbled_deepslate_stonecutting": {
    "criteria": {
      "has_cobbled_deepslate": "2026-02-11 01:36:21 +0000"
    },
    "done": true
  },
  "farmersdelight:recipes/cooking/squid_ink_pasta": {
    "criteria": {
      "has_any_ingredient": "2026-02-11 01:21:45 +0000"
    },
    "done": true
  },
  "minecraft:recipes/building_blocks/deepslate": {
    "criteria": {
      "has_cobbled_deepslate": "2026-02-11 01:36:21 +0000"
    },
    "done": true
  },
  "minecraft:recipes/decorations/white_carpet": {
    "criteria": {
      "has_white_wool": "2026-02-11 01:44:27 +0000"
    },
    "done": true
  },
  "minecraft:recipes/building_blocks/jack_o_lantern": {
    "criteria": {
      "has_carved_pumpkin": "2026-02-11 01:11:19 +0000"
    },
    "done": true
  },
  "minecraft:recipes/decorations/glass_pane": {
    "criteria": {
      "has_glass": "2026-02-11 01:09:02 +0000"
    },
    "done": true
  },
  "minecraft:recipes/building_blocks/magenta_stained_glass": {
    "criteria": {
      "has_glass": "2026-02-11 01:09:02 +0000"
    },
    "done": true
  },
  "minecraft:recipes/building_blocks/white_stained_glass": {
    "criteria": {
      "has_glass": "2026-02-11 01:09:02 +0000"
    },
    "done": true
  },
  "minecraft:recipes/building_blocks/andesite_slab_from_andesite_stonecutting": {
    "criteria": {
      "has_andesite": "2026-02-11 01:36:06 +0000"
    },
    "done": true
  },
  "minecraft:recipes/building_blocks/polished_deepslate_stairs_from_cobbled_deepslate_stonecutting": {
    "criteria": {
      "has_cobbled_deepslate": "2026-02-11 01:36:21 +0000"
    },
    "done": true
  },
  "minecraft:recipes/food/pumpkin_pie": {
    "criteria": {
      "has_carved_pumpkin": "2026-02-11 01:11:19 +0000"
    },
    "done": true
  },
  "minecraft:recipes/building_blocks/copper_block": {
    "criteria": {
      "has_copper_ingot": "2026-02-11 01:08:27 +0000"
    },
    "done": true
  },
  "farmersdelight:recipes/food/cooked_bacon_from_campfire_cooking": {
    "criteria": {
      "cooked_bacon": "2026-02-11 01:51:46 +0000"
    },
    "done": true
  },
  "minecraft:recipes/misc/gold_ingot_from_smelting_raw_gold": {
    "criteria": {
      "has_raw_gold": "2026-02-11 01:39:46 +0000"
    },
    "done": true
  },
  "minecraft:recipes/building_blocks/andesite_stairs_from_andesite_stonecutting": {
    "criteria": {
      "has_andesite": "2026-02-11 01:36:06 +0000"
    },
    "done": true
  },
  "minecraft:recipes/decorations/deepslate_brick_wall_from_cobbled_deepslate_stonecutting": {
    "criteria": {
      "has_cobbled_deepslate": "2026-02-11 01:36:21 +0000"
    },
    "done": true
  },
  "minecraft:recipes/building_blocks/red_stained_glass": {
    "criteria": {
      "has_glass": "2026-02-11 01:09:02 +0000"
    },
    "done": true
  },
  "farmersdelight:recipes/food/cooked_bacon_from_smoking": {
    "criteria": {
      "cooked_bacon": "2026-02-11 01:51:46 +0000"
    },
    "done": true
  },
  "minecraft:recipes/building_blocks/polished_deepslate_from_cobbled_deepslate_stonecutting": {
    "criteria": {
      "has_cobbled_deepslate": "2026-02-11 01:36:21 +0000"
    },
    "done": true
  },
  "minecraft:recipes/building_blocks/polished_deepslate_slab_from_cobbled_deepslate_stonecutting": {
    "criteria": {
      "has_cobbled_deepslate": "2026-02-11 01:36:21 +0000"
    },
    "done": true
  },
  "minecraft:recipes/tools/brush": {
    "criteria": {
      "has_copper_ingot": "2026-02-11 01:08:27 +0000"
    },
    "done": true
  },
  "minecraft:recipes/brewing/glass_bottle": {
    "criteria": {
      "has_glass": "2026-02-11 01:09:02 +0000"
    },
    "done": true
  },
  "farmersdelight:recipes/building_blocks/tomato_crate": {
    "criteria": {
      "has_tomato": "2026-02-11 01:21:45 +0000"
    },
    "done": true
  },
  "minecraft:recipes/building_blocks/raw_gold_block": {
    "criteria": {
      "has_raw_gold": "2026-02-11 01:39:46 +0000"
    },
    "done": true
  },
  "minecraft:recipes/brewing/fermented_spider_eye": {
    "criteria": {
      "has_spider_eye": "2026-02-11 01:31:33 +0000"
    },
    "done": true
  },
  "minecraft:recipes/building_blocks/deepslate_brick_slab_from_cobbled_deepslate_stonecutting": {
    "criteria": {
      "has_cobbled_deepslate": "2026-02-11 01:36:21 +0000"
    },
    "done": true
  },
  "minecraft:recipes/building_blocks/light_gray_stained_glass": {
    "criteria": {
      "has_glass": "2026-02-11 01:09:02 +0000"
    },
    "done": true
  },
  "minecraft:recipes/building_blocks/cobbled_deepslate_slab_from_cobbled_deepslate_stonecutting": {
    "criteria": {
      "has_cobbled_deepslate": "2026-02-11 01:36:21 +0000"
    },
    "done": true
  },
  "minecraft:recipes/food/cooked_mutton": {
    "criteria": {
      "has_mutton": "2026-02-11 01:44:27 +0000"
    },
    "done": true
  },
  "minecraft:recipes/building_blocks/deepslate_tile_slab_from_cobbled_deepslate_stonecutting": {
    "criteria": {
      "has_cobbled_deepslate": "2026-02-11 01:36:21 +0000"
    },
    "done": true
  },
  "minecraft:recipes/misc/red_dye_from_beetroot": {
    "criteria": {
      "has_beetroot": "2026-02-11 01:21:26 +0000"
    },
    "done": true
  },
  "minecraft:recipes/decorations/white_banner": {
    "criteria": {
      "has_white_wool": "2026-02-11 01:44:27 +0000"
    },
    "done": true
  },
  "minecraft:recipes/building_blocks/cobbled_deepslate_stairs": {
    "criteria": {
      "has_cobbled_deepslate": "2026-02-11 01:36:21 +0000"
    },
    "done": true
  },
  "minecraft:recipes/building_blocks/polished_andesite_from_andesite_stonecutting": {
    "criteria": {
      "has_andesite": "2026-02-11 01:36:06 +0000"
    },
    "done": true
  },
  "farmersdelight:recipes/food/cooked_mutton_chops_from_campfire_cooking": {
    "criteria": {
      "cooked_mutton_chops": "2026-02-11 01:50:50 +0000"
    },
    "done": true
  },
  "farmersdelight:recipes/food/mixed_salad": {
    "criteria": {
      "has_bowl": "2026-02-11 02:00:18 +0000"
    },
    "done": true
  },
  "farmersdelight:main/use_cutting_board": {
    "criteria": {
      "cutting_board": "2026-02-11 01:50:50 +0000"
    },
    "done": true
  },
  "minecraft:recipes/building_blocks/cyan_stained_glass": {
    "criteria": {
      "has_glass": "2026-02-11 01:09:02 +0000"
    },
    "done": true
  },
  "minecraft:recipes/building_blocks/polished_andesite": {
    "criteria": {
      "has_andesite": "2026-02-11 01:36:06 +0000"
    },
    "done": true
  },
  "minecraft:recipes/food/cooked_mutton_from_campfire_cooking": {
    "criteria": {
      "has_mutton": "2026-02-11 01:44:27 +0000"
    },
    "done": true
  },
  "farmersdelight:recipes/cooking/pasta_with_mutton_chop": {
    "criteria": {
      "has_any_ingredient": "2026-02-11 01:44:27 +0000"
    },
    "done": true
  },
  "minecraft:recipes/building_blocks/purple_stained_glass": {
    "criteria": {
      "has_glass": "2026-02-11 01:09:02 +0000"
    },
    "done": true
  },
  "minecraft:recipes/building_blocks/yellow_stained_glass": {
    "criteria": {
      "has_glass": "2026-02-11 01:09:02 +0000"
    },
    "done": true
  },
  "farmersdelight:recipes/cooking/tomato_sauce": {
    "criteria": {
      "has_tomato": "2026-02-11 01:21:45 +0000"
    },
    "done": true
  },
  "farmersdelight:recipes/misc/tomato_seeds": {
    "criteria": {
      "has_tomato": "2026-02-11 01:21:45 +0000"
    },
    "done": true
  },
  "minecraft:recipes/decorations/deepslate_tile_wall_from_cobbled_deepslate_stonecutting": {
    "criteria": {
      "has_cobbled_deepslate": "2026-02-11 01:36:21 +0000"
    },
    "done": true
  },
  "biomesoplenty:recipes/misc/white_dye_from_white_petals": {
    "criteria": {
      "has_flower": "2026-02-11 01:31:00 +0000"
    },
    "done": true
  },
  "minecraft:recipes/building_blocks/deepslate_bricks_from_cobbled_deepslate_stonecutting": {
    "criteria": {
      "has_cobbled_deepslate": "2026-02-11 01:36:21 +0000"
    },
    "done": true
  },
  "farmersdelight:recipes/cooking/beetroot_soup": {
    "criteria": {
      "has_beetroot": "2026-02-11 01:21:26 +0000"
    },
    "done": true
  },
  "minecraft:husbandry/plant_seed": {
    "criteria": {
      "beetroots": "2026-02-11 01:21:22 +0000"
    },
    "done": true
  },
  "farmersdelight:recipes/food/sweet_berry_cookie": {
    "criteria": {
      "has_sweet_berries": "2026-02-11 01:31:19 +0000"
    },
    "done": true
  },
  "minecraft:recipes/decorations/andesite_wall": {
    "criteria": {
      "has_andesite": "2026-02-11 01:36:06 +0000"
    },
    "done": true
  },
  "minecraft:recipes/building_blocks/andesite_slab": {
    "criteria": {
      "has_andesite": "2026-02-11 01:36:06 +0000"
    },
    "done": true
  },
  "minecraft:recipes/misc/wheat": {
    "criteria": {
      "has_hay_block": "2026-02-11 01:11:19 +0000"
    },
    "done": true
  },
  "minecraft:recipes/building_blocks/polished_andesite_stairs_from_andesite_stonecutting": {
    "criteria": {
      "has_andesite": "2026-02-11 01:36:06 +0000"
    },
    "done": true
  },
  "minecraft:recipes/decorations/white_bed": {
    "criteria": {
      "has_white_wool": "2026-02-11 01:44:27 +0000"
    },
    "done": true
  },
  "minecraft:recipes/food/mushroom_stew": {
    "criteria": {
      "has_bowl": "2026-02-11 02:00:18 +0000"
    },
    "done": true
  },
  "farmersdelight:recipes/building_blocks/cabbage_crate": {
    "criteria": {
      "has_cabbage": "2026-02-11 02:01:17 +0000"
    },
    "done": true
  },
  "farmersdelight:recipes/food/bacon_and_eggs": {
    "criteria": {
      "has_bacon": "2026-02-11 01:53:24 +0000"
    },
    "done": true
  },
  "minecraft:recipes/building_blocks/deepslate_tiles_from_cobbled_deepslate_stonecutting": {
    "criteria": {
      "has_cobbled_deepslate": "2026-02-11 01:36:21 +0000"
    },
    "done": true
  },
  "farmersdelight:recipes/food/cooked_bacon": {
    "criteria": {
      "cooked_bacon": "2026-02-11 01:51:46 +0000"
    },
    "done": true
  },
  "DataVersion": 3465
}